{"@context":"http://iiif.io/api/presentation/2/context.json","@type":"sc:Manifest","@id":"https://bvmm.irht.cnrs.fr/iiif/8551/manifest","viewingDirection":"left-to-right","viewingHint":"individuals","label":"TOURS, Bibliothèque municipale, 2273 B (Décor)","description":"","thumbnail":{"@id":"https://iiif.irht.cnrs.fr/iiif/ark:/63955/vug4sxer3y9w/full/200,/0/default.jpg","service":{"@context":"http://iiif.io/api/image/2/context.json","profile":"http://iiif.io/api/image/2/level2.json","@id":"https://iiif.irht.cnrs.fr/iiif/ark:/63955/vug4sxer3y9w"}},"metadata":[{"label":"Cote","value":"TOURS, Bibliothèque municipale, 2273 B"},{"label":"Auteur, titre, oeuvre","value":"Heures (fragment)"},{"label":"Support","value":"parchemin"},{"label":"Datation","value":"14e s. (seconde moitié)"},{"label":"Dimensions (mm)","value":"180 x 133"},{"label":"Foliotation","value":"1 f."},{"label":"Notes","value":""},{"label":"Provider","value":"Bibliothèque Virtuelle des Manuscrits Médiévaux (BVMM) &ndash; IRHT-CNRS"},{"label":"Source images","value":"https://bvmm.irht.cnrs.fr/resultRecherche/resultRecherche.php?COMPOSITION_ID=2659"},{"label":"Source métadonnées","value":"http://medium-avance.irht.cnrs.fr/ark:/63955/md09w0894z24"}],"license":"http://creativecommons.org/licenses/by-nc/3.0/deed.fr","attribution":"Bibliothèque municipale de TOURS","logo":"https://bvmm.irht.cnrs.fr/includes/interface/Titre-court-en-fontin-sans-ombres-.png","related":[],"seeAlso":"","within":"https://bvmm.irht.cnrs.fr/315556101/collection.json","sequences":[{"@id":"https://bvmm.irht.cnrs.fr/iiif/8551/sequence/default","@type":"sc:Sequence","label":"Décor","canvases":[{"@id":"https://bvmm.irht.cnrs.fr/iiif/8551/canvas/canvas-1269067","@type":"sc:Canvas","label":"Tours, Bibl. mun., ms. 2273 B, recto - vue 1","height":2960,"width":1984,"images":[{"@type":"oa:Annotation","motivation":"sc:painting","resource":{"@id":"https://iiif.irht.cnrs.fr/iiif/France/Tours/B372616101/DEPOT/IRHT_051362_2/full/full/0/default.jpg","@type":"dctypes:Image","format":"image/jpeg","height":2960,"width":1984,"service":{"@context":"http://iiif.io/api/image/2/context.json","@id":"https://iiif.irht.cnrs.fr/iiif/France/Tours/B372616101/DEPOT/IRHT_051362_2","profile":"http://iiif.io/api/image/2/level2.json"}},"on":"https://bvmm.irht.cnrs.fr/iiif/8551/canvas/canvas-1269067"}]},{"@id":"https://bvmm.irht.cnrs.fr/iiif/8551/canvas/canvas-1269066","@type":"sc:Canvas","label":"Tours, Bibl. mun., ms. 2273 B, recto - vue 2","height":2936,"width":1992,"images":[{"@type":"oa:Annotation","motivation":"sc:painting","resource":{"@id":"https://iiif.irht.cnrs.fr/iiif/France/Tours/B372616101/DEPOT/IRHT_051363_2/full/full/0/default.jpg","@type":"dctypes:Image","format":"image/jpeg","height":2936,"width":1992,"service":{"@context":"http://iiif.io/api/image/2/context.json","@id":"https://iiif.irht.cnrs.fr/iiif/France/Tours/B372616101/DEPOT/IRHT_051363_2","profile":"http://iiif.io/api/image/2/level2.json"}},"on":"https://bvmm.irht.cnrs.fr/iiif/8551/canvas/canvas-1269066"}]},{"@id":"https://bvmm.irht.cnrs.fr/iiif/8551/canvas/canvas-1269068","@type":"sc:Canvas","label":"Tours, Bibl. mun., ms. 2273 B, verso","height":2952,"width":1976,"images":[{"@type":"oa:Annotation","motivation":"sc:painting","resource":{"@id":"https://iiif.irht.cnrs.fr/iiif/France/Tours/B372616101/DEPOT/IRHT_051364_2/full/full/0/default.jpg","@type":"dctypes:Image","format":"image/jpeg","height":2952,"width":1976,"service":{"@context":"http://iiif.io/api/image/2/context.json","@id":"https://iiif.irht.cnrs.fr/iiif/France/Tours/B372616101/DEPOT/IRHT_051364_2","profile":"http://iiif.io/api/image/2/level2.json"}},"on":"https://bvmm.irht.cnrs.fr/iiif/8551/canvas/canvas-1269068"}]}]}]}